synchronizer/__init__.py
synchronizer/cli.py
synchronizer/fs_synchronizer.py
synchronizer/package_info.py
synchronizer/synchronizer.py
multiprocess_synchronizer-0.0.2rc0.dist-info/LICENSE
multiprocess_synchronizer-0.0.2rc0.dist-info/METADATA
multiprocess_synchronizer-0.0.2rc0.dist-info/WHEEL
multiprocess_synchronizer-0.0.2rc0.dist-info/entry_points.txt
multiprocess_synchronizer-0.0.2rc0.dist-info/top_level.txt
multiprocess_synchronizer-0.0.2rc0.dist-info/RECORD
