Metadata-Version: 2.1
Name: multiprocess-synchronizer
Version: 0.0.2rc0
Summary: A library to synchronize multiple processes in a distributed system.
Home-page: https://github.com/sandyhouse/synchronizer
Download-URL: https://github.com/sandyhouse/synchronizer/releases
Author: Long LI
Author-email: lilong.albert@gmail.com
Maintainer: Long LI
Maintainer-email: lilong.albert@gmail.com
License: Apache 2.0
Keywords: synchronization,distributed,multiprocessing
Classifier: Development Status :: 3 - Alpha
Classifier: Intended Audience :: Developers
Classifier: Intended Audience :: Science/Research
Classifier: Intended Audience :: Information Technology
Classifier: Topic :: Scientific/Engineering
Classifier: Topic :: Software Development :: Libraries
Classifier: Topic :: Software Development :: Libraries :: Python Modules
Classifier: Topic :: Utilities
Classifier: License :: OSI Approved :: Apache Software License
Classifier: Programming Language :: Python :: 3
Classifier: Programming Language :: Python :: 3.8
Classifier: Programming Language :: Python :: 3.9
Classifier: Programming Language :: Python :: 3.10
Classifier: Environment :: Console
Classifier: Natural Language :: English
Classifier: Operating System :: OS Independent
License-File: LICENSE
